pyglider/__init__.py
pyglider/_version.py
pyglider/example_data.py
pyglider/ncprocess.py
pyglider/seaexplorer.py
pyglider/slocum.py
pyglider/utils.py
pyglider-0.0.7.dist-info/LICENSE
pyglider-0.0.7.dist-info/METADATA
pyglider-0.0.7.dist-info/WHEEL
pyglider-0.0.7.dist-info/top_level.txt
pyglider-0.0.7.dist-info/zip-safe
pyglider-0.0.7.dist-info/RECORD
